LICENSE.txt
README.md
setup.py
ftwgl/__init__.py
ftwgl/api.py
ftwgl/enum.py
ftwgl/game_server.py
ftwgl/game_server_from_dict.py
ftwgl/rcon.py
ftwgl.egg-info/PKG-INFO
ftwgl.egg-info/SOURCES.txt
ftwgl.egg-info/dependency_links.txt
ftwgl.egg-info/requires.txt
ftwgl.egg-info/top_level.txt