Metadata-Version: 2.1
Name: ftwgl
Version: 0.1.18
Summary: FTW Python Client
Home-page: https://ftwgl.net
Author: solitary
Author-email: solitaryurt@gmail.com
License: MIT
Keywords: Gaming League,FTWGL
Classifier: Development Status :: 3 - Alpha
Classifier: Intended Audience :: Developers
Classifier: Topic :: Software Development :: Build Tools
Classifier: License :: OSI Approved :: MIT License
Classifier: Programming Language :: Python :: 3
Classifier: Programming Language :: Python :: 3.5
Classifier: Programming Language :: Python :: 3.6
Classifier: Programming Language :: Python :: 3.7
Classifier: Programming Language :: Python :: 3.8
Classifier: Programming Language :: Python :: 3.9
Classifier: Programming Language :: Python :: 3.10
License-File: LICENSE.txt
